[
  {
    "nomor": "6282261130248"
  },
  {
    "nomor": "6283138355050"
  },
  {
    "nomor": "6283141426475"
  },
  {
    "nomor": "6283848966859"
  },
  {
    "nomor": "6285601195471"
  },
  {
    "nomor": "6283895553195"
  },
  {
    "nomor": "6281295454040"
  },
  {
    "nomor": "6285135396260"
  },
  {
    "nomor": "6283134595491"
  },
  {
    "nomor": "6289516288657"
  },
  {
    "nomor": "6285813795248"
  },
  {
    "nomor": "6287771422078"
  },
  {
    "nomor": "6285184575036"
  },
  {
    "nomor": "6281263378183"
  },
  {
    "nomor": "62895325875236"
  },
  {
    "nomor": "6285654267147"
  },
  {
    "nomor": "6288212293864"
  },
  {
    "nomor": "6289672304306"
  },
  {
    "nomor": "6283875798931"
  },
  {
    "nomor": "6285142040816"
  },
  {
    "nomor": "6285727462791"
  },
  {
    "nomor": "6283166559282"
  },
  {
    "nomor": "6283139866559"
  },
  {
    "nomor": "601129919692"
  },
  {
    "nomor": "6288276703118"
  },
  {
    "nomor": "6288220710967"
  },
  {
    "nomor": "6283142036234"
  },
  {
    "nomor": "6288296174867"
  },
  {
    "nomor": "6285159400145"
  },
  {
    "nomor": "6285147059530"
  },
  {
    "nomor": "3197010517642"
  },
  {
    "nomor": "6282312885447"
  },
  {
    "nomor": "6283867648060"
  },
  {
    "nomor": "6283849428057"
  },
  {
    "nomor": "6282328607845"
  },
  {
    "nomor": "6289654812365"
  },
  {
    "nomor": "6283177812560"
  },
  {
    "nomor": "6285729894838"
  },
  {
    "nomor": "6282221860676"
  },
  {
    "nomor": "639918198506"
  },
  {
    "nomor": "6281328134697"
  },
  {
    "nomor": "6283893694686"
  },
  {
    "nomor": "601128597362"
  },
  {
    "nomor": "6285814168634"
  },
  {
    "nomor": "6285187695859"
  },
  {
    "nomor": "6285717364548"
  },
  {
    "nomor": "62895393992810"
  },
  {
    "nomor": "62895395331679"
  },
  {
    "nomor": "6282195295125"
  },
  {
    "nomor": "6285187982946"
  },
  {
    "nomor": "601159501223"
  },
  {
    "nomor": "6283878104828"
  },
  {
    "nomor": "6282130033771"
  },
  {
    "nomor": "201288096744"
  },
  {
    "nomor": "6285711180835"
  },
  {
    "nomor": "6285716799010"
  },
  {
    "nomor": "380996707897"
  },
  {
    "nomor": "6285811533511"
  },
  {
    "nomor": "6281542338487"
  },
  {
    "nomor": "6283852349296"
  },
  {
    "nomor": "6288705669313"
  }
]
